xstreamlib/__init__.py
xstreamlib/stream.py
xstreamlib/utils.py
xstreamlib-1.0.0.dist-info/licenses/LICENSE
xstreamlib-1.0.0.dist-info/METADATA
xstreamlib-1.0.0.dist-info/WHEEL
xstreamlib-1.0.0.dist-info/top_level.txt
xstreamlib-1.0.0.dist-info/RECORD
