Metadata-Version: 2.4
Name: xstreamlib
Version: 1.0.0
Summary: Librería para facilitar el streaming de archivos de XMedia y su api
Author-email: KeimaSenpai <KeimaSenpai@proton.me>
License:                     GNU GENERAL PUBLIC LICENSE
Project-URL: Homepage, https://github.com/KeimaSenpai
Project-URL: Documentation, https://github.com/KeimaSenpai
Project-URL: Source, https://github.com/KeimaSenpai
Project-URL: Issues, https://github.com/KeimaSenpai
Project-URL: Community, https://t.me/KeimaSenpai
License-File: LICENSE
Requires-Dist: requests
Dynamic: license-file
